bclm/__init__.py
bclm/evaluations.py
bclm/hebtokenizer.py
bclm/outputs.py
bclm/readers.py
bclm/transforms.py
bclm/data/__init__.py
bclm/data/sentence_align_map.csv.gz
bclm/data/spdf_fixed.csv.gz
bclm/data/spmrl_fixed.conllu
bclm/data/spmrl_tokens_df.csv.gz
bclm/data/token_morpheme_alignment_spmrl_ud_with_fixes.csv
bclm/data/ud_fixed.conllu
bclm/data/uddf_fixed.csv.gz
bclm/data/yap_outputs/spmrl_dev.lattices
bclm/data/yap_outputs/spmrl_dev_dep.conll
bclm/data/yap_outputs/spmrl_dev_map.conll
bclm/data/yap_outputs/spmrl_dev_seg.conll
bclm/data/yap_outputs/spmrl_dev_tokens.txt
bclm/data/yap_outputs/spmrl_test.lattices
bclm/data/yap_outputs/spmrl_test_dep.conll
bclm/data/yap_outputs/spmrl_test_map.conll
bclm/data/yap_outputs/spmrl_test_seg.conll
bclm/data/yap_outputs/spmrl_test_tokens.txt
bclm/data/yap_outputs/spmrl_train_tokens.txt
bclm/data/yap_outputs/yap_dev.csv.gz
bclm/data/yap_outputs/yap_dev_tokens.csv.gz
bclm/data/yap_outputs/yap_test.csv.gz
bclm/data/yap_outputs/yap_test_tokens.csv.gz
bclm-1.0.0.dist-info/LICENSE
bclm-1.0.0.dist-info/METADATA
bclm-1.0.0.dist-info/WHEEL
bclm-1.0.0.dist-info/top_level.txt
bclm-1.0.0.dist-info/RECORD
