Metadata-Version: 2.1
Name: bclm
Version: 1.0.0
Summary: THE go-to place for all Python Hebrew Treebank processing tasks.
Home-page: https://github.com/cjer/bclm
Author: Dan Bareket
Author-email: dbareket@gmail.com
License: UNKNOWN
Platform: UNKNOWN
Classifier: Programming Language :: Python :: 3
Classifier: License :: OSI Approved :: MIT License
Classifier: Operating System :: OS Independent
Requires-Dist: pandas
Requires-Dist: conllu
Requires-Dist: numpy
